jsonfp/__init__.py
jsonfp-0.0.1.dist-info/METADATA
jsonfp-0.0.1.dist-info/WHEEL
jsonfp-0.0.1.dist-info/top_level.txt
jsonfp-0.0.1.dist-info/RECORD
