Metadata-Version: 2.1
Name: jsonfp
Version: 0.0.1
Summary: TBD
Author-email: 4d <4d@tumbleweeds.xyz>
Classifier: Programming Language :: Python :: 3
Classifier: License :: OSI Approved :: MIT License
Classifier: Operating System :: OS Independent
Requires-Python: >=3.8
Requires-Dist: setuptools >=41.6
